{
    "metadata": {
        "source": "tradition_to_contemporary.pdf",
        "page": 10,
        "name": "tradition_to_contemporary_page_10",
        "images": []
    },
    "document": "次於 1988 年登黄山後所繪的《滿江紅》，便在其施用石膏或石綠時，讓青綠浮在墨色上，改變了對青綠的運用方法；若墨色遮住了留白，他還會用白色將原本要留白的地方填染，雖然主觀成份較五十年代的作品多，但重精神描寫和氣韻表達。其大部分晚年山水作品，均結合青綠山水和水墨寫意，用中鋒線條構建骨骼和勾勒部分山石輪廓，配合濃墨濃彩，創其獨有著著功、色彩絢麗、氣魄過人的雄渾氣格，並具備他典型注重寫生，喜作濃墨濃彩的特色。 \n另一國家級大師作品是 1983 年 12 月賴少其 (1915- 2000) 訪問香港時，贈予馬平山博物館的《黃山》(圖版 48) 圖，屬於他退休前、中後期的作品。賴氏是首位推薦和研究黃賓虹作品的董事人物。《黃山》用墨濃重，構圖繁密，近似黃賓虹八十歲後（即 1945 年）的風，密、厚重，意境深遠的「黑賓虹」畫風。賴氏的個人特點是著於表現光影和混合水墨和色彩，再配以焦墨和書法線條入畫，且稍見拙重，這些都允仿表現在《黃山》一作上。 \n至於方石潭的山水和風俗畫，與別不同，別具一格，例如 1988 年作的《山水》(圖版 52)，除有強烈的書法用筆外，更需題段跋，並將之與畫面山石結合，而《龍舟競渡》和平須之六)（圖版 49）則色彩斑斕，稚拙可愛，顯露童心。 \n其他本地畫家，如潘振華（1936 年生）、盧玉燕、彭蕙清和劉鈐等，則各具特色，但大多受西方現代繪畫的構圖和技巧影響。例如彭蕙清的《琉璃世界》（圖版 77）便能夠糅合傳統國畫重視筆墨的堅持，承傳張大千（1899- 1983）的潑墨山水畫技法。 \n## 嶺南畫派和廣東「國畫研究會」 \n縱觀整個二十世紀的香港畫壇，除了傳統派山水畫或廣東畫家的作品外，能由始至終、根深柢固地影響嶺南畫壇逾百年，發展至今的莫過於是嶺南畫派。嶺南畫派主張革新和折衷中外繪畫技法，創「撞水撞粉」之法，是在改造傳統國畫或水墨畫外，另一個新的發展方向。 \n藏品中雖然沒有高劍父、高奇峰和陳樹人的嶺南畫派創始人作品，但有其祖師居巢（1811- 1865）和同門師弟容祖椿（1871- 1942）的沒骨花鳥作品。居民的繪畫風格是當時嶺南地區的主流畫風，而容祖椿則是廣東「國畫研究會」的代表，這兩位畫家在香港大學美術館的藏品，透現出嶺南畫派和廣東國畫研究會早在十九世紀中後期已對香港和廣東畫壇有相當的影響。 \n至於代表嶺南畫派的作品則有第二代越少昂的《花鳥》（圖版 27）冊頁、繁雄才（1910- 2001）的《春江泛滬》（圖版 44）、葉少乘（1896- 1968）贈周千秋和梁榮燦的《花蝶》（圖版 23）； \n5 轉引自江蘇常州《劉海墨的水山作品賞》(3)：1988年7月，劉海墨後來在送他上士山作畫的體會時說：「在資館作畫，水墨和筆彩均有，但為借黃山氣勢，直抒老大胸臆，墨是潑墨，彩是潑墨，筆是塗筆，我上士山最得意的佳趣是：黃山之奇，奇在雲崖里；黃山之險，險在松壑間；黃山之妙，妙在有無間；黃山之趣，趣在微雨里；黃山之瀑，瀑在幾處。」劉姓 http://blog.sina.com.cn/s/blog_bc5d48180l2vupic.html. Accessed on 20 July 2018. \n6 國畫研究會，是民國時期在廣東境內會員最多、活動時間較長、影響力較大的畫家社團，以研究和振興國畫為宗旨，並鼓勵學術研究的組織，除了廣州，在東莞和香港也有分會，成員不限廣東畫家，或某家某派，該會成立於1926年的廣州，活動至1938年日軍侵華廣州陷為止，轉引自朱萬章，後「聚英合作畫社」到「國畫研究會」——近現代美術語境中的嶺南傳統畫家，《文藝研究》，2008, (12): 120- 136。\n\n",
    "id": "b96658e63e748d5086eb504259a0565d"
}