{
    "document": "# 罐  \n\n中國，明嘉靖，一五四五年，或十九世紀\n\n青花瓷， $, \\ 3 1 \\ \\mathrm { ~ x ~ } \\ 3 0 $ 厘米\n\nHKU.C.1992.0967  \n\n此為大酒罐。體積特大、飾有精巧花紋的罐通常為御園裝飾物，也是深受十四世紀的中東與東南亞地區歡迎的外銷瓷；類似器皿可見於伊朗的阿爾達比勒神廟、和泰國南奔的瑪哈泰寺。  \n\n中心位置書「大明嘉靖乙巳年江西景德鎮造」款，表明它製於嘉靖二十四年，即一五四五年──不過直到十九世紀，當地仍有燒造相類的罐。青花罐的器型在元明兩代經歷顯著的變化。與十四世紀的大多數同類的低肩、間或配有短手柄的器物相比，此罐之頸部明顯較寬。雖然轉枝花卉紋是明中葉瓷器的典型花紋，但象徵美麗、力量與明宮廷的孔雀紋卻是較特別的。  \n\n![](objectifying_china/21_2.jpeg)",
    "id": "413d91cbd7301bb5b3ffdf3b8ee6793c",
    "metadata": {
        "name": "罐",
        "description": "中國，明嘉靖，一五四五年，或十九世紀\n\n青花瓷， $, \\ 3 1 \\ \\mathrm { ~ x ~ } \\ 3 0 $ 厘米\n\nHKU.C.1992.0967  \n\n此為大酒罐。體積特大、飾有精巧花紋的罐通常為御園裝飾物，也是深受十四世紀的中東與東南亞地區歡迎的外銷瓷；類似器皿可見於伊朗的阿爾達比勒神廟、和泰國南奔的瑪哈泰寺。  \n\n中心位置書「大明嘉靖乙巳年江西景德鎮造」款，表明它製於嘉靖二十四年，即一五四五年──不過直到十九世紀，當地仍有燒造相類的罐。青花罐的器型在元明兩代經歷顯著的變化。與十四世紀的大多數同類的低肩、間或配有短手柄的器物相比，此罐之頸部明顯較寬。雖然轉枝花卉紋是明中葉瓷器的典型花紋，但象徵美麗、力量與明宮廷的孔雀紋卻是較特別的。",
        "source": "objectifying_china",
        "images": [
            "21_2.jpeg"
        ]
    }
}